eval_hub_sdk-0.1.0a0.dist-info/licenses/LICENSE
evalhub/__init__.py
evalhub/cli.py
evalhub/py.typed
evalhub/adapter/__init__.py
evalhub/adapter/cli.py
evalhub/adapter/api/__init__.py
evalhub/adapter/api/endpoints.py
evalhub/adapter/api/router.py
evalhub/adapter/client/__init__.py
evalhub/adapter/client/adapter_client.py
evalhub/adapter/client/discovery.py
evalhub/adapter/models/__init__.py
evalhub/adapter/models/framework.py
evalhub/adapter/oci/__init__.py
evalhub/adapter/oci/persister.py
evalhub/adapter/server/__init__.py
evalhub/adapter/server/app.py
evalhub/models/__init__.py
evalhub/models/api.py
evalhub/utils/__init__.py
evalhub/utils/logging.py
eval_hub_sdk-0.1.0a0.dist-info/METADATA
eval_hub_sdk-0.1.0a0.dist-info/WHEEL
eval_hub_sdk-0.1.0a0.dist-info/entry_points.txt
eval_hub_sdk-0.1.0a0.dist-info/top_level.txt
eval_hub_sdk-0.1.0a0.dist-info/RECORD
