Metadata-Version: 2.4
Name: eval-hub-sdk
Version: 0.1.0a0
Summary: SDK for building framework adapters that integrate with TrustyAI EvalHub
Author-email: Rui Vieira <rui@redhat.com>
Project-URL: Homepage, https://github.com/eval-hub
Project-URL: Repository, https://github.com/eval-hub/eval-hub-sdk
Project-URL: Documentation, https://github.com/eval-hub/eval-hub-sdk
Project-URL: Bug Tracker, https://github.com/eval-hub/eval-hub-sdk/issues
Keywords: ai,evaluation,framework,sdk,trustyai
Classifier: Development Status :: 4 - Beta
Classifier: Intended Audience :: Developers
Classifier: License :: OSI Approved :: Apache Software License
Classifier: Operating System :: OS Independent
Classifier: Programming Language :: Python :: 3
Classifier: Programming Language :: Python :: 3.10
Classifier: Programming Language :: Python :: 3.11
Classifier: Programming Language :: Python :: 3.12
Classifier: Topic :: Scientific/Engineering :: Artificial Intelligence
Classifier: Topic :: Software Development :: Libraries :: Python Modules
Requires-Python: >=3.10
License-File: LICENSE
Requires-Dist: pydantic>=2.0.0
Requires-Dist: importlib-metadata>=6.0.0
Provides-Extra: core
Requires-Dist: httpx>=0.25.0; extra == "core"
Provides-Extra: adapter
Requires-Dist: eval-hub-sdk[core]; extra == "adapter"
Requires-Dist: fastapi>=0.104.0; extra == "adapter"
Requires-Dist: uvicorn[standard]>=0.24.0; extra == "adapter"
Provides-Extra: client
Requires-Dist: eval-hub-sdk[core]; extra == "client"
Provides-Extra: cli
Requires-Dist: eval-hub-sdk[core]; extra == "cli"
Requires-Dist: typer>=0.9.0; extra == "cli"
Requires-Dist: rich>=13.0.0; extra == "cli"
Provides-Extra: dev
Requires-Dist: pytest>=7.4.0; extra == "dev"
Requires-Dist: pytest-asyncio>=0.21.0; extra == "dev"
Requires-Dist: pytest-cov>=4.1.0; extra == "dev"
Requires-Dist: ruff==0.1.6; extra == "dev"
Requires-Dist: mypy==1.7.1; extra == "dev"
Requires-Dist: pre-commit>=3.4.0; extra == "dev"
Provides-Extra: examples
Requires-Dist: lm-eval>=0.4.0; extra == "examples"
Requires-Dist: ragas>=0.1.0; extra == "examples"
Provides-Extra: all
Requires-Dist: eval-hub-sdk[adapter,cli,client,core,dev]; extra == "all"
Dynamic: license-file
